logoturtle/__init__.py
logoturtle/__main__.py
logoturtle/main.py
logoturtle/parsing.py
logoturtle-1.3.6.dist-info/DESCRIPTION.rst
logoturtle-1.3.6.dist-info/METADATA
logoturtle-1.3.6.dist-info/RECORD
logoturtle-1.3.6.dist-info/WHEEL
logoturtle-1.3.6.dist-info/metadata.json
logoturtle-1.3.6.dist-info/top_level.txt
