Metadata-Version: 2.0
Name: logoturtle
Version: 1.3.6
Summary: A simple, education videogame to move a turtle with Turtle module. It's a Turtle wrapper.
Home-page: UNKNOWN
Author: Elia Toselli S.
Author-email: elia.toselli@outlook.it
License: GPL
Platform: UNKNOWN
